marshmallow_models/__init__.py
marshmallow_models/compat.py
marshmallow_models/field_descriptor.py
marshmallow_models/models.py
marshmallow_models-0.2.0.dist-info/DESCRIPTION.rst
marshmallow_models-0.2.0.dist-info/METADATA
marshmallow_models-0.2.0.dist-info/RECORD
marshmallow_models-0.2.0.dist-info/WHEEL
marshmallow_models-0.2.0.dist-info/metadata.json
marshmallow_models-0.2.0.dist-info/top_level.txt
