Metadata-Version: 2.0
Name: marshmallow-models
Version: 0.2.0
Summary: Object models with validation and serialization using Marshmallow fields and validators.
Home-page: https://github.com/douglas-treadwell/marshmallow-models
Author: Douglas Treadwell
Author-email: douglas.treadwell@gmail.com
License: MIT
Keywords: serialization,rest,json,api,marshal,marshalling,deserialization,validation,schema,model,models,modelling,object,objects
Platform: UNKNOWN
Classifier: Development Status :: 3 - Alpha
Classifier: Intended Audience :: Developers
Classifier: License :: OSI Approved :: MIT License
Classifier: Programming Language :: Python :: 2
Classifier: Programming Language :: Python :: 2.7
Classifier: Programming Language :: Python :: 3
Classifier: Programming Language :: Python :: 3.4
Classifier: Programming Language :: Python :: 3.5
Classifier: Programming Language :: Python :: 3.6
Classifier: Programming Language :: Python :: Implementation :: CPython
Classifier: Programming Language :: Python :: Implementation :: PyPy
Requires-Dist: marshmallow
